langconnect/__init__.py
langconnect/__main__.py
langconnect/auth.py
langconnect/config.py
langconnect/server.py
langconnect/api/__init__.py
langconnect/api/auth.py
langconnect/api/collections.py
langconnect/api/documents.py
langconnect/database/__init__.py
langconnect/database/collections.py
langconnect/database/connection.py
langconnect/models/__init__.py
langconnect/models/collection.py
langconnect/models/document.py
langconnect/services/__init__.py
langconnect/services/document_processor.py
mseep_langconnect_client-0.0.2.dist-info/METADATA
mseep_langconnect_client-0.0.2.dist-info/WHEEL
mseep_langconnect_client-0.0.2.dist-info/entry_points.txt
mseep_langconnect_client-0.0.2.dist-info/licenses/LICENSE
mseep_langconnect_client-0.0.2.dist-info/RECORD
