Metadata-Version: 2.4
Name: mseep-langconnect-client
Version: 0.0.2
Summary: LangConnect Client: GUI interface for managing knowledge bases and connected to RAG service
Author-email: mseep <support@skydeck.ai>
License-File: LICENSE
Requires-Python: >=3.11
Requires-Dist: aiohttp>=3.11.13
Requires-Dist: asyncpg>=0.30.0
Requires-Dist: beautifulsoup4>=4.12.3
Requires-Dist: email-validator>=2.1.0
Requires-Dist: fastapi>=0.115.6
Requires-Dist: fastmcp>=0.1.0
Requires-Dist: httpx>=0.28.1
Requires-Dist: langchain-community>=0.0.20
Requires-Dist: langchain-core>=0.2.37
Requires-Dist: langchain-openai>=0.3.7
Requires-Dist: langchain-postgres>=0.0.2
Requires-Dist: langchain-text-splitters>=0.0.1
Requires-Dist: langchain>=0.3.20
Requires-Dist: langgraph-sdk>=0.1.48
Requires-Dist: lxml>=5.4.0
Requires-Dist: pandas>=2.2.0
Requires-Dist: pdfminer-six>=20231228
Requires-Dist: pdfminer-six>=20250416
Requires-Dist: pdfplumber>=0.11.0
Requires-Dist: pillow>=11.2.1
Requires-Dist: psycopg[binary]>=3.2.6
Requires-Dist: python-docx>=1.1.0
Requires-Dist: python-dotenv>=1.0.1
Requires-Dist: python-multipart>=0.0.20
Requires-Dist: requests>=2.31.0
Requires-Dist: supabase>=2.15.1
Requires-Dist: unstructured[docx]>=0.17.2
Requires-Dist: uvicorn>=0.34.0
